{
	"0": {
		"2024.10.17": {
			"0": {
				"생활관식당(블루미르308관)": {
					"조식(양식)": {
						"price": "5,000 원",
						"time": "07:40~08:40",
						"menu": "쌀밥|크림스프|돈까스*소스|모닝빵*딸기잼|그린샐러드*드레싱|깍두기"
					}
				}
			},
			"1": {
				"참슬기식당(310관 B4층)": {
					"중식(한식)": {
						"price": "4,000 원",
						"time": "11:00~13:30",
						"menu": "개교108주년"
					},
					"중식(특식)": {
						"price": "5,500 원",
						"time": "11:30~13:30",
						"menu": "개교108주년"
					}
				},
				"생활관식당(블루미르308관)": {
					"중식(한식)": {
						"price": "5,500 원",
						"time": "11:30~13:30",
						"menu": "바지락들깨칼국수|추가밥|만두강정|모듬야채겉절이|깍두기|그린샐러드*드레싱"
					}
				},
				"생활관식당(블루미르309관)": {
					"중식(한식)": {
						"price": "7,000 원",
						"time": "11:00~13:30",
						"menu": "개교기념일|운영없음"
					},
					"중식(양식)": {
						"price": "7,000 원",
						"time": "11:00~13:30",
						"menu": ""
					},
					"중식(특식)": {
						"price": "6,000 원",
						"time": "11:00~13:30",
						"menu": ""
					}
				},
				"학생식당(303관B1층)": {
					"중식(한식)": {
						"price": "5,500 원",
						"time": "11:00~13:30",
						"menu": "개교기념일(운영없음)"
					}
				}
			},
			"2": {
				"참슬기식당(310관 B4층)": {
					"": {
						"price": "4,000 원"
					},
					"석식(석식)": {
						"price": "5,500 원",
						"time": "17:00~18:30",
						"menu": "개교108주년"
					}
				},
				"생활관식당(블루미르308관)": {
					"석식(한식)": {
						"price": "5,500 원",
						"time": "17:30~19:00",
						"menu": "쌀밥|순두부찌개|파채너비아니구이|새송이버섯볶음|고들빼기무침|깍두기|그린샐러드*드레싱"
					}
				},
				"생활관식당(블루미르309관)": {
					"석식(한식)": {
						"price": "7,000 원",
						"time": "16:30~18:30",
						"menu": "개교기념일|운영없음"
					},
					"석식(양식)": {
						"price": "7,000 원",
						"time": "16:30~18:30",
						"menu": ""
					},
					"석식(특식)": {
						"price": "6,000 원",
						"time": "16:30~18:30",
						"menu": ""
					}
				}
			}
		},
		"2024.10.18": {
			"0": {
				"생활관식당(블루미르308관)": {
					"조식(한식)": {
						"price": "5,000 원",
						"time": "07:40~08:40",
						"menu": "쌀밥|닭곰탕|부추전|감자조림|양파초절임|석박지"
					}
				}
			},
			"1": {
				"참슬기식당(310관 B4층)": {
					"중식(한식)": {
						"price": "4,000 원",
						"time": "11:00~13:30",
						"menu": "치킨데리야끼덮밥|고로케*케찹|단무지"
					},
					"중식(특식)": {
						"price": "5,500 원",
						"time": "11:30~13:30",
						"menu": "소고기미역국|주꾸미삼겹볶음|고로케*케찹|천사채마요샐러드|부추겉절이|김치"
					}
				},
				"생활관식당(블루미르308관)": {
					"중식(한식)": {
						"price": "5,500 원",
						"time": "11:30~13:30",
						"menu": "삼겹김치볶음밥|우동국물|오징어링튀김*타르소스|후식음료|열무김치|그린샐러드*드레싱"
					}
				},
				"생활관식당(블루미르309관)": {
					"중식(한식)": {
						"price": "7,000 원",
						"time": "11:00~13:30",
						"menu": "참치비빔밥|삼겹살비빔밥|육회비빔밥|차돌비빔밥"
					},
					"중식(양식)": {
						"price": "7,000 원",
						"time": "11:00~13:30",
						"menu": "우동|왕새우튀김우동|소고기우동|우동+유부3종|새우튀김우동+유부3종|소고기우동+유부3종|유부초밥3종|얼큰김치우동|옛날왕돈가스정식"
					},
					"중식(특식)": {
						"price": "6,000 원",
						"time": "11:00~13:30",
						"menu": "씽푸짜장면|새우볶음밥|씽푸짬뽕|수제탕수육|고추짜장면|탕짜면|탕짬면|찐만두|만두튀김"
					}
				},
				"학생식당(303관B1층)": {
					"중식(한식)": {
						"price": "5,500 원",
						"time": "11:00~13:30",
						"menu": "햄김치볶음밥|미니온우동|미니돈까스*케첩|도토리묵*양념장|반달단무지무침|그린야채샐러드(사과드레싱)|깍두기"
					},
					"중식(단품1)": {
						"price": "3,500 원",
						"time": "11:30~14:00",
						"menu": "기본라면"
					},
					"중식(단품2)": {
						"price": "4,200 원",
						"time": "11:30~14:00",
						"menu": "치즈라면|계란라면|만두라면|해장라면|떡라면"
					},
					"중식(단품3)": {
						"price": "4,700 원",
						"time": "11:30~14:00",
						"menu": "순두부라면"
					},
					"중식(단품4)": {
						"price": "5,000 원",
						"time": "11:30~14:00",
						"menu": "돼지불고기라면"
					},
					"중식(단품5)": {
						"price": "4,500 원",
						"time": "11:30~14:00",
						"menu": "짜파게티"
					},
					"중식(단품6)": {
						"price": "5,000 원",
						"time": "11:30~14:00",
						"menu": "짜계치"
					},
					"중식(단품7)": {
						"price": "8,000 원",
						"time": "11:30~14:00",
						"menu": "소불고기짜파게티"
					},
					"중식(단품8)": {
						"price": "5,500 원",
						"time": "11:30~14:00",
						"menu": "돼지고기김치찌개"
					},
					"중식(단품9)": {
						"price": "3,500 원",
						"time": "11:30~14:00",
						"menu": "마요존밥(토핑추가가능)"
					},
					"중식(양식1)": {
						"price": "5,000 원",
						"time": "11:30~14:00",
						"menu": "오므라이스(토핑추가가능)"
					},
					"중식(양식2)": {
						"price": "6,000 원",
						"time": "11:30~14:00",
						"menu": "비건함박스테이크"
					},
					"중식(양식3)": {
						"price": "6,000 원",
						"time": "11:30~14:00",
						"menu": "생선까스"
					},
					"중식(양식4)": {
						"price": "6,000 원",
						"time": "11:30~14:00",
						"menu": "통등심돈까스"
					},
					"중식(양식5)": {
						"price": "6,500 원",
						"time": "11:30~14:00",
						"menu": "통살치킨까스"
					},
					"중식(양식6)": {
						"price": "5,500 원",
						"time": "11:30~14:00",
						"menu": "도토리묵포케"
					},
					"중식(양식7)": {
						"price": "6,300 원",
						"time": "11:30~14:00",
						"menu": "숯불구이소세지포케"
					},
					"중식(양식8)": {
						"price": "6,500 원",
						"time": "11:30~14:00",
						"menu": "닭가슴살소세지포케"
					},
					"중식(양식9)": {
						"price": "7,500 원",
						"time": "11:30~14:00",
						"menu": "제육볶음포케"
					},
					"중식(양식10)": {
						"price": "8,000 원",
						"time": "11:30~14:00",
						"menu": "소불고기포케"
					}
				},
				"University Club(102관11층)": {
					"중식(한식1)": {
						"price": "11,000 원",
						"time": "11:30~14:00",
						"menu": "돼지고기묵은지김치찌개"
					},
					"중식(한식2)": {
						"price": "13,500 원",
						"time": "11:30~14:00",
						"menu": "사골황태설렁탕"
					},
					"중식(한식3)": {
						"price": "15,000 원",
						"time": "11:30~14:00",
						"menu": "치즈돈까스정식(샐러드포함)"
					},
					"중식(한식4)": {
						"price": "16,000 원",
						"time": "11:30~14:00",
						"menu": "철판불쭈꾸미정식(비빔용기제공)"
					},
					"중식(한식5)": {
						"price": "18,000 원",
						"time": "11:30~14:00",
						"menu": "매운돼지갈비찜과솥밥정식"
					}
				}
			},
			"2": {
				"참슬기식당(310관 B4층)": {
					"석식(학생석식)": {
						"price": "4,000 원",
						"time": "17:00~18:30",
						"menu": "카레라이스|소세지칠리볶음|깍두기"
					},
					"석식(석식)": {
						"price": "5,500 원",
						"time": "17:00~18:30",
						"menu": "우거지된장국|삼치데리야끼구이|소세지칠리볶음|브로콜리다시마초회|깍두기|오렌지주스"
					}
				},
				"생활관식당(블루미르308관)": {
					"석식(한식)": {
						"price": "5,500 원",
						"time": "17:30~19:00",
						"menu": "쌀밥|근대된장국|간장불고기|야채계란찜|양념깻잎지|배추김치|그린샐러드*드레싱"
					}
				},
				"생활관식당(블루미르309관)": {
					"석식(한식)": {
						"price": "7,000 원",
						"time": "16:30~18:30",
						"menu": "참치비빔밥|삼겹살비빔밥|육회비빔밥|차돌비빔밥"
					},
					"석식(양식)": {
						"price": "7,000 원",
						"time": "16:30~18:30",
						"menu": "우동|왕새우튀김우동|소고기우동|우동+유부3종|새우튀김우동+유부3종|소고기우동+유부3종|유부초밥3종|얼큰김치우동|옛날왕돈가스정식"
					},
					"석식(특식)": {
						"price": "6,000 원",
						"time": "16:30~18:30",
						"menu": "씽푸짜장면|새우볶음밥|씽푸짬뽕|수제탕수육|고추짜장면|탕짜면|탕짬면|찐만두|만두튀김"
					}
				}
			}
		},
		"2024.10.19": {
			"0": {
				"생활관식당(블루미르308관)": {
					"조식(양식)": {
						"price": "5,000 원",
						"time": "08:00~09:00",
						"menu": "빵3종*딸기잼|시리얼|소시지구이*머스타드|그린샐러드*드레싱|우유|요플레"
					}
				}
			},
			"1": {
				"생활관식당(블루미르308관)": {
					"중식(특식)": {
						"price": "5,500 원",
						"time": "11:30~13:00",
						"menu": "쌀밥|계란파국|짜장소스|탕수육|단무지무침|배추김치|그린샐러드*드레싱"
					}
				},
				"생활관식당(블루미르309관)": {
					"중식(한식)": {
						"price": "0 원",
						"time": "11:00~13:30",
						"menu": ""
					},
					"중식(양식)": {
						"price": "0 원",
						"time": "11:00~13:30",
						"menu": ""
					},
					"중식(특식)": {
						"price": "0 원",
						"time": "11:00~13:30",
						"menu": ""
					}
				}
			},
			"2": {
				"생활관식당(블루미르308관)": {
					"석식(양식)": {
						"price": "5,500 원",
						"time": "17:30~18:30",
						"menu": "쌀밥|콘스프|함박스테이크*소스|펜네크림파스타|오이피클|깍두기|그린샐러드*드레싱"
					}
				},
				"생활관식당(블루미르309관)": {
					"석식(한식)": {
						"price": "0 원",
						"time": "16:30~18:30",
						"menu": ""
					},
					"석식(양식)": {
						"price": "0 원",
						"time": "16:30~18:30",
						"menu": ""
					},
					"석식(특식)": {
						"price": "0 원",
						"time": "16:30~18:30",
						"menu": ""
					}
				}
			}
		},
		"2024.10.20": {
			"0": {
				"생활관식당(블루미르308관)": {
					"조식(양식)": {
						"price": "5,000 원",
						"time": "08:00~09:00",
						"menu": "빵3종*딸기잼|시리얼|계란후라이|그린샐러드*드레싱|우유|바나나"
					}
				}
			},
			"1": {
				"생활관식당(블루미르308관)": {
					"중식(한식)": {
						"price": "5,500 원",
						"time": "11:30~13:00",
						"menu": "순대국|쌀밥|동그랑땡조림|얼갈이된장나물|석박지|그린샐러드*드레싱"
					}
				},
				"생활관식당(블루미르309관)": {
					"중식(한식)": {
						"price": "0 원",
						"time": "11:00~13:30",
						"menu": ""
					},
					"중식(양식)": {
						"price": "0 원",
						"time": "11:00~13:30",
						"menu": ""
					},
					"중식(특식)": {
						"price": "0 원",
						"time": "11:00~13:30",
						"menu": ""
					}
				}
			},
			"2": {
				"생활관식당(블루미르308관)": {
					"석식(한식)": {
						"price": "5,500 원",
						"time": "17:30~18:30",
						"menu": "쌀밥|돈육김치찌개|한식잡채|견과류멸치볶음|다시마튀각|깍두기|그린샐러드*드레싱"
					}
				},
				"생활관식당(블루미르309관)": {
					"석식(한식)": {
						"price": "0 원",
						"time": "16:30~18:30",
						"menu": ""
					},
					"석식(양식)": {
						"price": "0 원",
						"time": "16:30~18:30",
						"menu": ""
					},
					"석식(특식)": {
						"price": "0 원",
						"time": "16:30~18:30",
						"menu": ""
					}
				}
			}
		},
		"2024.10.21": {
			"0": {
				"참슬기식당(310관 B4층)": {}
			},
			"1": {
				"참슬기식당(310관 B4층)": {}
			},
			"2": {
				"참슬기식당(310관 B4층)": {}
			}
		},
		"2024.10.22": {
			"0": {
				"참슬기식당(310관 B4층)": {}
			},
			"1": {
				"참슬기식당(310관 B4층)": {}
			},
			"2": {
				"참슬기식당(310관 B4층)": {}
			}
		},
		"2024.10.23": {
			"0": {
				"참슬기식당(310관 B4층)": {}
			},
			"1": {
				"참슬기식당(310관 B4층)": {}
			},
			"2": {
				"참슬기식당(310관 B4층)": {}
			}
		}
	},
	"1": {
		"2024.10.17": {
			"0": {
				"카우잇츠(cau eats)": {
					"조식(한식)": {
						"price": "5,000 원",
						"time": "08:10~09:10",
						"menu": ""
					}
				},
				"(안성)카우버거": {
					"조식": {
						"price": "0 원",
						"time": "08:40~09:20",
						"menu": "<천원의빵>블루베리베이글|커피set"
					},
					"조식(중식)": {
						"price": "0 원",
						"time": "09:30~16:30",
						"menu": "햄버거/사이드/커피및음료/아이스크림"
					}
				},
				"(안성)라면": {
					"조식": {
						"price": "2,500 원",
						"time": "06:00~11:00",
						"menu": "신라면|너구리|진라면매운맛|안성탕면"
					}
				}
			},
			"1": {
				"카우잇츠(cau eats)": {
					"중식(특식)": {
						"price": "5,500 원",
						"time": "11:30~14:00",
						"menu": ""
					},
					"중식(일품1)": {
						"price": "4,000 원",
						"time": "11:30~14:00",
						"menu": ""
					}
				},
				"(안성)라면": {
					"중식(중식)": {
						"price": "2,500 원",
						"time": "11:00~16:00",
						"menu": "신라면|너구리|진라면매운맛|안성탕면"
					}
				}
			},
			"2": {
				"카우잇츠(cau eats)": {
					"석식(특식)": {
						"price": "5,500 원",
						"time": "17:00~18:30",
						"menu": ""
					},
					"석식(일품1)": {
						"price": "4,000 원",
						"time": "17:00~18:30",
						"menu": ""
					}
				},
				"(안성)카우버거": {
					"석식(석식)": {
						"price": "0 원",
						"time": "16:30~18:30",
						"menu": "햄버거/사이드/커피및음료/아이스크림"
					}
				},
				"(안성)라면": {
					"석식(석식)": {
						"price": "2,500 원",
						"time": "16:01~23:00",
						"menu": "신라면|너구리|진라면매운맛|안성탕면"
					}
				}
			}
		},
		"2024.10.18": {
			"0": {
				"카우잇츠(cau eats)": {
					"조식(한식)": {
						"price": "5,000 원",
						"time": "08:10~09:10",
						"menu": ""
					}
				},
				"(안성)카우버거": {
					"조식": {
						"price": "0 원",
						"time": "08:40~09:20",
						"menu": ""
					},
					"조식(중식)": {
						"price": "0 원",
						"time": "09:30~16:30",
						"menu": "햄버거/사이드/커피및음료/아이스크림"
					}
				},
				"(안성)라면": {
					"조식": {
						"price": "2,500 원",
						"time": "06:00~11:00",
						"menu": "신라면|너구리|진라면매운맛|안성탕면"
					}
				}
			},
			"1": {
				"카우잇츠(cau eats)": {
					"중식(특식)": {
						"price": "5,500 원",
						"time": "11:30~14:00",
						"menu": "소고기미역국|주꾸미삼겹볶음|고로케*케찹|천사채마요샐러드|부추겉절이|김치"
					},
					"중식(일품1)": {
						"price": "4,000 원",
						"time": "11:30~14:00",
						"menu": "치킨데리야끼덮밥|고로케*케찹|단무지"
					}
				},
				"(안성)라면": {
					"중식(중식)": {
						"price": "2,500 원",
						"time": "11:00~16:00",
						"menu": "신라면|너구리|진라면매운맛|안성탕면"
					}
				}
			},
			"2": {
				"카우잇츠(cau eats)": {
					"석식(특식)": {
						"price": "5,500 원",
						"time": "17:00~18:30",
						"menu": "우거지된장국|삼치데리야끼구이|소세지칠리볶음|브로콜리다시마초회|깍두기|오렌지주스"
					},
					"석식(일품1)": {
						"price": "4,000 원",
						"time": "17:00~18:30",
						"menu": "카레라이스|소세지칠리볶음|깍두기"
					}
				},
				"(안성)카우버거": {
					"석식(석식)": {
						"price": "0 원",
						"time": "16:30~18:30",
						"menu": "햄버거/사이드/커피및음료/아이스크림"
					}
				},
				"(안성)라면": {
					"석식(석식)": {
						"price": "2,500 원",
						"time": "16:01~23:00",
						"menu": "신라면|너구리|진라면매운맛|안성탕면"
					}
				}
			}
		},
		"2024.10.19": {
			"0": {
				"(안성)라면": {
					"조식": {
						"price": "2,500 원",
						"time": "06:00~11:00",
						"menu": "신라면|너구리|진라면매운맛|안성탕면"
					}
				}
			},
			"1": {
				"(안성)라면": {
					"중식(중식)": {
						"price": "2,500 원",
						"time": "11:00~16:00",
						"menu": "신라면|너구리|진라면매운맛|안성탕면"
					}
				}
			},
			"2": {
				"(안성)라면": {
					"석식(석식)": {
						"price": "2,500 원",
						"time": "16:01~23:00",
						"menu": "신라면|너구리|진라면매운맛|안성탕면"
					}
				}
			}
		},
		"2024.10.20": {
			"0": {
				"(안성)라면": {
					"조식": {
						"price": "2,500 원",
						"time": "06:00~11:00",
						"menu": "신라면|너구리|진라면매운맛|안성탕면"
					}
				}
			},
			"1": {
				"(안성)라면": {
					"중식(중식)": {
						"price": "2,500 원",
						"time": "11:00~16:00",
						"menu": "신라면|너구리|진라면매운맛|안성탕면"
					}
				}
			},
			"2": {
				"(안성)라면": {
					"석식(석식)": {
						"price": "2,500 원",
						"time": "16:01~23:00",
						"menu": "신라면|너구리|진라면매운맛|안성탕면"
					}
				}
			}
		},
		"2024.10.21": {
			"0": {
				"카우잇츠(cau eats)": {}
			},
			"1": {
				"카우잇츠(cau eats)": {}
			},
			"2": {
				"카우잇츠(cau eats)": {}
			}
		},
		"2024.10.22": {
			"0": {
				"카우잇츠(cau eats)": {}
			},
			"1": {
				"카우잇츠(cau eats)": {}
			},
			"2": {
				"카우잇츠(cau eats)": {}
			}
		},
		"2024.10.23": {
			"0": {
				"카우잇츠(cau eats)": {}
			},
			"1": {
				"카우잇츠(cau eats)": {}
			},
			"2": {
				"카우잇츠(cau eats)": {}
			}
		}
	}
}