{
	"0": {
		"2023.12.24": {
			"0": {
				"생활관식당(블루미르308관)": {
					"조식(양식)": {
						"price": "4,500 원",
						"time": "08:00~09:00",
						"menu": "빵3종*버터|시리얼|해쉬브라운|그린샐러드*드레싱|우유|요플레"
					}
				}
			},
			"1": {
				"생활관식당(블루미르308관)": {
					"중식(한식)": {
						"price": "5,500 원",
						"time": "11:30~13:00",
						"menu": "쌀밥|호박고추장국|간장불고기|오징어파전|콩나물무침|깍두기|그린샐러드*드레싱"
					}
				},
				"생활관식당(블루미르309관)": {
					"중식(한식)": {
						"price": "0 원",
						"time": "11:00~13:30",
						"menu": ""
					},
					"중식(양식)": {
						"price": "0 원",
						"time": "11:00~13:30",
						"menu": ""
					},
					"중식(특식)": {
						"price": "0 원",
						"time": "11:00~13:30",
						"menu": ""
					}
				}
			},
			"2": {
				"생활관식당(블루미르308관)": {
					"석식(특식)": {
						"price": "5,500 원",
						"time": "17:30~18:30",
						"menu": "쌀밥|팽이장국|치킨가스*머스타드|쫄면야채무침|간장마늘쫑지|깍두기|그린샐러드*드레싱"
					}
				},
				"생활관식당(블루미르309관)": {
					"석식(한식)": {
						"price": "0 원",
						"time": "16:30~18:30",
						"menu": ""
					},
					"석식(양식)": {
						"price": "0 원",
						"time": "16:30~18:30",
						"menu": ""
					},
					"석식(특식)": {
						"price": "0 원",
						"time": "16:30~18:30",
						"menu": ""
					}
				}
			}
		},
		"2023.12.25": {
			"0": {
				"생활관식당(블루미르308관)": {
					"조식(한식)": {
						"price": "4,500 원",
						"time": "08:00~09:00",
						"menu": "쌀밥|순두부백탕|고등어구이|햄야채볶음|도시락김|깍두기"
					}
				}
			},
			"1": {
				"생활관식당(블루미르308관)": {
					"중식(한식)": {
						"price": "5,500 원",
						"time": "11:30~13:00",
						"menu": "쌀밥|다시마무국|매콤닭갈비|사각어묵볶음|오이생채|배추김치|그린샐러드*드레싱"
					}
				},
				"학생식당(303관B1층)": {
					"중식(한식)": {
						"price": "5,500 원",
						"time": "11:00~13:30",
						"menu": "운영없음(메리크리스마스)"
					}
				}
			},
			"2": {
				"생활관식당(블루미르308관)": {
					"": {}
				}
			}
		},
		"2023.12.26": {
			"0": {
				"생활관식당(블루미르308관)": {
					"조식(한식)": {
						"price": "4,500 원",
						"time": "07:30~08:40",
						"menu": "쌀밥|감자양파국|너비아니구이|명엽채고추장볶음|마늘쫑지|배추김치"
					}
				}
			},
			"1": {
				"생활관식당(블루미르308관)": {
					"중식(한식)": {
						"price": "5,500 원",
						"time": "11:30~13:30",
						"menu": "쌀밥|호박고추장국|간장불고기|야채계란찜|양배추쌈*쌈장|배추김치|그린샐러드*드레싱"
					}
				},
				"학생식당(303관B1층)": {
					"중식(한식)": {
						"price": "5,500 원",
						"time": "11:00~13:30",
						"menu": "잡곡밥|크림스프|토마토스파게티|미트볼폭찹|수제피클|그린야채샐러드|배추김치"
					}
				},
				"University Club(102관11층)": {
					"중식(한식1)": {
						"price": "10,000 원",
						"time": "11:30~14:00",
						"menu": "꽃게순두부찌개"
					},
					"중식(한식2)": {
						"price": "13,000 원",
						"time": "11:30~14:00",
						"menu": "사골황태설렁탕"
					},
					"중식(한식3)": {
						"price": "15,000 원",
						"time": "11:30~14:00",
						"menu": "소고기짜장면과미니탕수육"
					},
					"중식(한식4)": {
						"price": "18,000 원",
						"time": "11:30~14:00",
						"menu": "매운돼지갈비찜과솥밥정식"
					},
					"중식(한식5)": {
						"price": "16,000 원",
						"time": "11:30~14:00",
						"menu": "허브삼겹살구이(식사메뉴X)"
					}
				}
			},
			"2": {
				"생활관식당(블루미르308관)": {
					"석식(한식)": {
						"price": "5,500 원",
						"time": "17:30~19:00",
						"menu": "나물비빔밥|시래기된장국|만두강정|후식음료|배추김치|그린샐러드*드레싱"
					}
				}
			}
		},
		"2023.12.27": {
			"0": {
				"생활관식당(블루미르308관)": {
					"조식(한식)": {
						"price": "4,500 원",
						"time": "07:30~08:40",
						"menu": "쌀밥|콩나물국|제육볶음|청포묵김가루무침|궁채절임|깍두기"
					}
				}
			},
			"1": {
				"생활관식당(블루미르308관)": {
					"중식(한식)": {
						"price": "5,500 원",
						"time": "11:30~13:30",
						"menu": "김치우동|추가밥|새우볼꼬치|단무지|열무김치|그린샐러드*드레싱"
					}
				},
				"학생식당(303관B1층)": {
					"중식(한식)": {
						"price": "5,500 원",
						"time": "11:00~13:30",
						"menu": "잡곡밥|맑은미역국|김치제육볶음|한식잡채|겨자콩나물무침|그린야채샐러드|배추김치"
					}
				},
				"University Club(102관11층)": {
					"중식(한식1)": {
						"price": "10,000 원",
						"time": "11:30~14:00",
						"menu": "꽃게순두부찌개"
					},
					"중식(한식2)": {
						"price": "13,000 원",
						"time": "11:30~14:00",
						"menu": "사골황태설렁탕"
					},
					"중식(한식3)": {
						"price": "15,000 원",
						"time": "11:30~14:00",
						"menu": "소고기짜장면과미니탕수육"
					},
					"중식(한식4)": {
						"price": "18,000 원",
						"time": "11:30~14:00",
						"menu": "매운돼지갈비찜과솥밥정식"
					},
					"중식(한식5)": {
						"price": "16,000 원",
						"time": "11:30~14:00",
						"menu": "허브삼겹살구이(식사메뉴X)"
					}
				}
			},
			"2": {
				"생활관식당(블루미르308관)": {
					"석식(한식)": {
						"price": "5,500 원",
						"time": "17:30~19:00",
						"menu": "쌀밥|청국장찌개|비엔나케찹볶음|연근조림|숙주나물|깍두기|그린샐러드*드레싱"
					}
				}
			}
		},
		"2023.12.28": {
			"0": {
				"생활관식당(블루미르308관)": {
					"조식(한식)": {
						"price": "4,500 원",
						"time": "07:30~08:40",
						"menu": "쌀밥|미역국|소불고기|연두부*양념장|모듬겉절이|배추김치"
					}
				}
			},
			"1": {
				"생활관식당(블루미르308관)": {
					"중식(한식)": {
						"price": "5,500 원",
						"time": "11:30~13:30",
						"menu": "훈제오리볶음밥|가쓰오장국|야채비빔면|코울슬로|깍두기|그린샐러드*드레싱"
					}
				},
				"학생식당(303관B1층)": {
					"중식(한식)": {
						"price": "5,500 원",
						"time": "11:00~13:30",
						"menu": "잡곡밥|덮밥용유산슬|파송송계란국|탕수육*간장소스|짜사이야채무침|그린야채샐러드|배추김치"
					}
				},
				"University Club(102관11층)": {
					"중식(한식1)": {
						"price": "10,000 원",
						"time": "11:30~14:00",
						"menu": "꽃게순두부찌개"
					},
					"중식(한식2)": {
						"price": "13,000 원",
						"time": "11:30~14:00",
						"menu": "사골황태설렁탕"
					},
					"중식(한식3)": {
						"price": "15,000 원",
						"time": "11:30~14:00",
						"menu": "소고기짜장면과미니탕수육"
					},
					"중식(한식4)": {
						"price": "18,000 원",
						"time": "11:30~14:00",
						"menu": "매운돼지갈비찜과솥밥정식"
					},
					"중식(한식5)": {
						"price": "16,000 원",
						"time": "11:30~14:00",
						"menu": "허브삼겹살구이(식사메뉴X)"
					}
				}
			},
			"2": {
				"생활관식당(블루미르308관)": {
					"석식(한식)": {
						"price": "5,500 원",
						"time": "17:30~19:00",
						"menu": "쌀밥|부대찌개|동그랑땡조림|돌자반볶음|아삭고추된장무침|깍두기|그린샐러드*드레싱"
					}
				}
			}
		},
		"2023.12.29": {
			"0": {
				"생활관식당(블루미르308관)": {
					"조식(한식)": {
						"price": "4,500 원",
						"time": "07:30~08:40",
						"menu": "낙지김치죽|열무물김치|메추리알장조림|고들빼기지|콩조림|깍두기"
					}
				}
			},
			"1": {
				"생활관식당(블루미르308관)": {
					"중식(특식)": {
						"price": "5,500 원",
						"time": "11:30~13:30",
						"menu": "치킨마요덮밥|팽이된장국|피자토스트|후식음료|배추김치|그린샐러드*드레싱"
					}
				},
				"학생식당(303관B1층)": {
					"중식(한식)": {
						"price": "5,500 원",
						"time": "11:00~13:30",
						"menu": "잡곡밥|김치콩나물국|순살돈까스*케첩|굴소스볶음우동|건새우마늘쫑볶음|그린야채샐러드|배추김치"
					}
				},
				"University Club(102관11층)": {
					"중식(한식1)": {
						"price": "10,000 원",
						"time": "11:30~14:00",
						"menu": "꽃게순두부찌개"
					},
					"중식(한식2)": {
						"price": "13,000 원",
						"time": "11:30~14:00",
						"menu": "사골황태설렁탕"
					},
					"중식(한식3)": {
						"price": "15,000 원",
						"time": "11:30~14:00",
						"menu": "소고기짜장면과미니탕수육"
					},
					"중식(한식4)": {
						"price": "18,000 원",
						"time": "11:30~14:00",
						"menu": "매운돼지갈비찜과솥밥정식"
					},
					"중식(한식5)": {
						"price": "16,000 원",
						"time": "11:30~14:00",
						"menu": "허브삼겹살구이(식사메뉴X)"
					}
				}
			},
			"2": {
				"생활관식당(블루미르308관)": {
					"석식(양식)": {
						"price": "5,500 원",
						"time": "17:30~19:00",
						"menu": "쌀밥|크림스프|생선가스*타르타르s|푸실리샐러드|오이피클|깍두기|그린샐러드*드레싱"
					}
				}
			}
		},
		"2023.12.30": {
			"0": {
				"생활관식당(블루미르308관)": {
					"조식(양식)": {
						"price": "4,500 원",
						"time": "08:00~09:00",
						"menu": "빵3종*딸기잼|시리얼|소시지구이*머스타드s|그린샐러드*드레싱|우유|사과"
					}
				}
			},
			"1": {
				"생활관식당(블루미르308관)": {
					"중식(특식)": {
						"price": "5,500 원",
						"time": "11:30~13:00",
						"menu": "쌀밥|유부맑은국|카레소스|고구마튀김|단무지무침|배추김치|그린샐러드*드레싱"
					}
				}
			},
			"2": {
				"생활관식당(블루미르308관)": {
					"석식(한식)": {
						"price": "5,500 원",
						"time": "17:30~18:30",
						"menu": "동태탕|쌀밥|미트볼케찹조림|간장고추지|배추김치|그린샐러드*드레싱"
					}
				}
			}
		}
	},
	"1": {
		"2023.12.24": {
			"0": {
				"(안성)라면": {
					"조식": {
						"price": "2,500 원",
						"time": "06:00~11:00",
						"menu": "신라면|너구리|틈새라면|안성탕면"
					}
				}
			},
			"1": {
				"(안성)라면": {
					"중식(중식)": {
						"price": "2,500 원",
						"time": "11:00~16:00",
						"menu": "신라면|너구리|틈새라면|안성탕면"
					}
				}
			},
			"2": {
				"(안성)라면": {
					"석식(석식)": {
						"price": "2,500 원",
						"time": "16:01~23:00",
						"menu": "신라면|너구리|틈새라면|안성탕면"
					}
				}
			}
		},
		"2023.12.25": {
			"0": {
				"(안성)카우버거": {
					"조식": {
						"price": "0 원",
						"time": "08:40~09:20",
						"menu": ""
					},
					"조식(중식)": {
						"price": "0 원",
						"time": "10:30~16:30",
						"menu": ""
					}
				},
				"(안성)라면": {
					"조식": {
						"price": "2,500 원",
						"time": "06:00~11:00",
						"menu": "신라면|너구리|틈새라면|안성탕면"
					}
				}
			},
			"1": {
				"카우잇츠(cau eats)": {
					"중식(특식)": {
						"price": "5,500 원",
						"time": "11:30~13:30",
						"menu": ""
					},
					"중식(일품1)": {
						"price": "4,000 원",
						"time": "11:30~13:30",
						"menu": ""
					}
				},
				"(안성)라면": {
					"중식(중식)": {
						"price": "2,500 원",
						"time": "11:00~16:00",
						"menu": "신라면|너구리|틈새라면|안성탕면"
					}
				}
			},
			"2": {
				"카우잇츠(cau eats)": {
					"석식(특식)": {
						"price": "5,500 원",
						"time": "17:30~18:30",
						"menu": ""
					},
					"석식(일품1)": {
						"price": "4,000 원",
						"time": "17:30~18:30",
						"menu": ""
					}
				},
				"(안성)카우버거": {
					"석식(석식)": {
						"price": "0 원",
						"time": "16:30~18:30",
						"menu": ""
					}
				},
				"(안성)라면": {
					"석식(석식)": {
						"price": "2,500 원",
						"time": "16:01~23:00",
						"menu": "신라면|너구리|틈새라면|안성탕면"
					}
				}
			}
		},
		"2023.12.26": {
			"0": {
				"(안성)카우버거": {
					"조식": {
						"price": "0 원",
						"time": "08:40~09:20",
						"menu": ""
					},
					"조식(중식)": {
						"price": "0 원",
						"time": "09:30~16:30",
						"menu": "햄버거/사이드/커피및음료/아이스크림"
					}
				},
				"(안성)라면": {
					"조식": {
						"price": "2,500 원",
						"time": "06:00~11:00",
						"menu": "신라면|너구리|틈새라면|안성탕면"
					}
				}
			},
			"1": {
				"카우잇츠(cau eats)": {
					"중식(특식)": {
						"price": "5,500 원",
						"time": "11:30~13:30",
						"menu": "콩나물국|소고기당면볶음|생선까스*타르소스|파인애플|알타리김치"
					},
					"중식(일품1)": {
						"price": "4,000 원",
						"time": "11:30~13:30",
						"menu": "함박스테이크|생선까스*타르소스|야채샐러드|김치|콩나물국"
					}
				},
				"(안성)라면": {
					"중식(중식)": {
						"price": "2,500 원",
						"time": "11:00~16:00",
						"menu": "신라면|너구리|틈새라면|안성탕면"
					}
				}
			},
			"2": {
				"카우잇츠(cau eats)": {
					"석식(특식)": {
						"price": "5,500 원",
						"time": "17:30~18:30",
						"menu": "닭갈비야채덮밥|단호박샐러드|깍두기|가쓰오국|들기름막국수|오이생채"
					},
					"석식(일품1)": {
						"price": "4,000 원",
						"time": "17:30~18:30",
						"menu": "닭갈비야채덮밥|단호박샐러드|깍두기|가쓰오국"
					}
				},
				"(안성)카우버거": {
					"석식(석식)": {
						"price": "0 원",
						"time": "16:30~18:30",
						"menu": ""
					}
				},
				"(안성)라면": {
					"석식(석식)": {
						"price": "2,500 원",
						"time": "16:01~23:00",
						"menu": "신라면|너구리|틈새라면|안성탕면"
					}
				}
			}
		},
		"2023.12.27": {
			"0": {
				"(안성)카우버거": {
					"조식": {
						"price": "0 원",
						"time": "08:40~09:20",
						"menu": ""
					},
					"조식(중식)": {
						"price": "0 원",
						"time": "09:30~16:30",
						"menu": "햄버거/사이드/커피및음료/아이스크림"
					}
				},
				"(안성)라면": {
					"조식": {
						"price": "2,500 원",
						"time": "06:00~11:00",
						"menu": "신라면|너구리|틈새라면|안성탕면"
					}
				}
			},
			"1": {
				"카우잇츠(cau eats)": {
					"중식(특식)": {
						"price": "5,500 원",
						"time": "11:30~13:30",
						"menu": "닭칼국수|녹두전|도토리묵야채무침|김치|유자생강차"
					},
					"중식(일품1)": {
						"price": "4,000 원",
						"time": "11:30~13:30",
						"menu": "가라아게동|쥬시쿨|단무지"
					}
				},
				"(안성)라면": {
					"중식(중식)": {
						"price": "2,500 원",
						"time": "11:00~16:00",
						"menu": "신라면|너구리|틈새라면|안성탕면"
					}
				}
			},
			"2": {
				"카우잇츠(cau eats)": {
					"석식(특식)": {
						"price": "5,500 원",
						"time": "17:30~18:30",
						"menu": "순두부찌개|고로케*케찹|깍두기|가자미구이|참나물참깨무침"
					},
					"석식(일품1)": {
						"price": "4,000 원",
						"time": "17:30~18:30",
						"menu": "순두부찌개|고로케*케찹|깍두기"
					}
				},
				"(안성)카우버거": {
					"석식(석식)": {
						"price": "0 원",
						"time": "16:30~18:30",
						"menu": ""
					}
				},
				"(안성)라면": {
					"석식(석식)": {
						"price": "2,500 원",
						"time": "16:01~01:00",
						"menu": "신라면|너구리|틈새라면|안성탕면"
					}
				}
			}
		},
		"2023.12.28": {
			"0": {
				"(안성)카우버거": {
					"조식": {
						"price": "0 원",
						"time": "08:40~09:20",
						"menu": ""
					},
					"조식(중식)": {
						"price": "0 원",
						"time": "09:30~16:30",
						"menu": "햄버거/사이드/커피및음료/아이스크림"
					}
				},
				"(안성)라면": {
					"조식": {
						"price": "2,500 원",
						"time": "06:00~11:00",
						"menu": "신라면|너구리|틈새라면|안성탕면"
					}
				}
			},
			"1": {
				"카우잇츠(cau eats)": {
					"중식(특식)": {
						"price": "5,500 원",
						"time": "11:30~13:30",
						"menu": "소고기미역국|콩불볶음|고기산적데리조림|숙주나물무침|도시락김|깍두기"
					},
					"중식(일품1)": {
						"price": "4,000 원",
						"time": "11:30~13:30",
						"menu": "육개장|고기산적데리조림|도시락김"
					}
				},
				"(안성)라면": {
					"중식(중식)": {
						"price": "2,500 원",
						"time": "11:00~16:00",
						"menu": "신라면|너구리|틈새라면|안성탕면"
					}
				}
			},
			"2": {
				"카우잇츠(cau eats)": {
					"석식(특식)": {
						"price": "5,500 원",
						"time": "17:30~18:30",
						"menu": "돈육김치덮밥|핫도그*케찹|단무지|홍합국|연두부샐러드|멸치볶음|메추리알조림"
					},
					"석식(일품1)": {
						"price": "4,000 원",
						"time": "17:30~18:30",
						"menu": "돈육김치덮밥|핫도그*케찹|단무지|홍합국"
					}
				},
				"(안성)카우버거": {
					"석식(석식)": {
						"price": "0 원",
						"time": "16:30~18:30",
						"menu": ""
					}
				},
				"(안성)라면": {
					"석식(석식)": {
						"price": "2,500 원",
						"time": "16:01~01:00",
						"menu": "신라면|너구리|틈새라면|안성탕면"
					}
				}
			}
		},
		"2023.12.29": {
			"0": {
				"(안성)카우버거": {
					"조식": {
						"price": "0 원",
						"time": "08:40~09:20",
						"menu": ""
					},
					"조식(중식)": {
						"price": "0 원",
						"time": "09:30~16:30",
						"menu": "햄버거/사이드/커피및음료/아이스크림"
					}
				},
				"(안성)라면": {
					"조식": {
						"price": "2,500 원",
						"time": "06:00~11:00",
						"menu": "신라면|너구리|틈새라면|안성탕면"
					}
				}
			},
			"1": {
				"카우잇츠(cau eats)": {
					"중식(특식)": {
						"price": "5,500 원",
						"time": "11:30~13:30",
						"menu": "오징어무국|제육볶음|만두탕수|건파래무침|깻잎지|김치"
					},
					"중식(일품1)": {
						"price": "4,000 원",
						"time": "11:30~13:30",
						"menu": "짜장덮밥|만두탕수|김치|계란국"
					}
				},
				"(안성)라면": {
					"중식(중식)": {
						"price": "2,500 원",
						"time": "11:00~16:00",
						"menu": "신라면|너구리|틈새라면|안성탕면"
					}
				}
			},
			"2": {
				"카우잇츠(cau eats)": {
					"석식(특식)": {
						"price": "5,500 원",
						"time": "17:30~18:30",
						"menu": "등심돈까스|요구르트|야채샐러드|김치|꼬치어묵우동|파인애플"
					},
					"석식(일품1)": {
						"price": "4,000 원",
						"time": "17:30~18:30",
						"menu": "등심돈까스|요구르트|야채샐러드|김치"
					}
				},
				"(안성)카우버거": {
					"석식(석식)": {
						"price": "0 원",
						"time": "16:30~18:30",
						"menu": ""
					}
				},
				"(안성)라면": {
					"석식(석식)": {
						"price": "2,500 원",
						"time": "16:01~01:00",
						"menu": "신라면|너구리|틈새라면|안성탕면"
					}
				}
			}
		},
		"2023.12.30": {
			"0": {
				"(안성)라면": {
					"조식": {
						"price": "2,500 원",
						"time": "06:00~11:00",
						"menu": "신라면|너구리|틈새라면|안성탕면"
					}
				}
			},
			"1": {
				"(안성)라면": {
					"중식(중식)": {
						"price": "2,500 원",
						"time": "11:00~16:00",
						"menu": "신라면|너구리|틈새라면|안성탕면"
					}
				}
			},
			"2": {
				"(안성)라면": {
					"석식(석식)": {
						"price": "2,500 원",
						"time": "16:01~23:00",
						"menu": "신라면|너구리|틈새라면|안성탕면"
					}
				}
			}
		}
	}
}